hiphip/__init__.py
hiphip/http.py
hiphip/decorators/json_response_body.py
hiphip/decorators/__init__.py
hiphip-0.1.2.dist-info/WHEEL
hiphip-0.1.2.dist-info/metadata.json
hiphip-0.1.2.dist-info/top_level.txt
hiphip-0.1.2.dist-info/DESCRIPTION.rst
hiphip-0.1.2.dist-info/RECORD
hiphip-0.1.2.dist-info/METADATA
