Metadata-Version: 2.0
Name: hiphip
Version: 0.1.2
Summary: UNKNOWN
Home-page: https://github.com/nikitanovosibirsk/hiphip
Author: Nikita Tsvetkov
Author-email: nikitanovosibirsk@yandex.com
License: MIT
Platform: UNKNOWN
Requires-Dist: requests (>=2.2.1)
